fibonacci_calculator_mpu/__init__.py
fibonacci_calculator_mpu/cli.py
fibonacci_calculator_mpu/main.py
fibonacci_calculator_mpu/test.py
fibonacci_calculator_mpu/Calculator/FibonacciIteration.py
fibonacci_calculator_mpu/Calculator/FibonacciRecursion.py
fibonacci_calculator_mpu/Calculator/__init__.py
fibonacci_calculator_mpu/Decorators/__init__.py
fibonacci_calculator_mpu/Decorators/memoize.py
fibonacci_calculator_mpu/tests/__init__.py
fibonacci_calculator_mpu/tests/test_calculators.py
fibonacci_calculator_mpu-0.0.2.dist-info/AUTHORS.rst
fibonacci_calculator_mpu-0.0.2.dist-info/LICENSE
fibonacci_calculator_mpu-0.0.2.dist-info/METADATA
fibonacci_calculator_mpu-0.0.2.dist-info/WHEEL
fibonacci_calculator_mpu-0.0.2.dist-info/entry_points.txt
fibonacci_calculator_mpu-0.0.2.dist-info/top_level.txt
fibonacci_calculator_mpu-0.0.2.dist-info/RECORD
