Metadata-Version: 2.1
Name: fibonacci-calculator-mpu
Version: 0.0.2
Summary: First PyPi package. Fibonacci Calculator. 
Home-page: https://github.com/MaartenUijen/fibonacci_calculator_mpu
Author: Maarten Uijen
Author-email: maarten.uijen@ordina.nl
License: MIT license
Keywords: fibonacci_calculator_mpu
Platform: UNKNOWN
Classifier: Development Status :: 2 - Pre-Alpha
Classifier: Intended Audience :: Developers
Classifier: License :: OSI Approved :: MIT License
Classifier: Natural Language :: English
Classifier: Programming Language :: Python :: 3
Classifier: Programming Language :: Python :: 3.5
Classifier: Programming Language :: Python :: 3.6
Classifier: Programming Language :: Python :: 3.7
Classifier: Programming Language :: Python :: 3.8
Requires-Python: >=3.5
Requires-Dist: Click (>=7.0)
